[
  {
    "School": "Adlai Stevenson",
    "Coach": "Chip Tompson",
    "Email": "rtompson@d125.org",
    "Phone": "+1 847-372-9182",
    "Congress": "",
    "Lincoln-Douglas": "",
    "Public Forum": "x",
    "Policy": ""
  },
  {
    "School": "Adlai Stevenson",
    "Coach": "Elisa Galvan Alba",
    "Email": "egalvan@d125.org",
    "Phone": "+1 224-436-5775",
    "Congress": "x",
    "Lincoln-Douglas": "",
    "Public Forum": "x",
    "Policy": ""
  },
  {
    "School": "Adlai Stevenson",
    "Coach": "Kaitlyn Remian",
    "Email": "kremian@d125.org",
    "Phone": "+1 847-254-0161",
    "Congress": "x",
    "Lincoln-Douglas": "",
    "Public Forum": "x",
    "Policy": ""
  },
  {
    "School": "Amos Alonzo Stagg",
    "Coach": "Katy Przybylski",
    "Email": "kprzybylski@d230.org",
    "Phone": "",
    "Congress": "",
    "Lincoln-Douglas": "x",
    "Public Forum": "x",
    "Policy": ""
  },
  {
    "School": "Andrew",
    "Coach": "Marta Leshyk",
    "Email": "mleshyk@d230.org",
    "Phone": "",
    "Congress": "",
    "Lincoln-Douglas": "x",
    "Public Forum": "x",
    "Policy": ""
  },
  {
    "School": "Aurora West High School",
    "Coach": "Cyndi White",
    "Email": "cynthia.white@sd129.org",
    "Phone": "+1 773-680-1700",
    "Congress": "",
    "Lincoln-Douglas": "x",
    "Public Forum": "x",
    "Policy": ""
  },
  {
    "School": "Barrington",
    "Coach": "Amy Lovi",
    "Email": "alovi@barrington220.org",
    "Phone": "",
    "Congress": "",
    "Lincoln-Douglas": "x",
    "Public Forum": "",
    "Policy": ""
  },
  {
    "School": "Belleville East",
    "Coach": "Joe Blasdel",
    "Email": "jeblasdel@mckendree.edu",
    "Phone": "+1 618-973-0030",
    "Congress": "",
    "Lincoln-Douglas": "x",
    "Public Forum": "x",
    "Policy": ""
  },
  {
    "School": "Belleville West",
    "Coach": "Brandon Hentze",
    "Email": "bhentze@bths201.org",
    "Phone": "+1 618-567-8976",
    "Congress": "x",
    "Lincoln-Douglas": "x",
    "Public Forum": "x",
    "Policy": ""
  },
  {
    "School": "Belvidere North",
    "Coach": "Nicole Kroepel",
    "Email": "nkroepel@district100.com",
    "Phone": "+1 847-877-0816",
    "Congress": "",
    "Lincoln-Douglas": "x",
    "Public Forum": "x",
    "Policy": ""
  },
  {
    "School": "Benet Academy",
    "Coach": "Lisa Savage",
    "Email": "lsavage@benet.org",
    "Phone": "+1 630-788-7124",
    "Congress": "",
    "Lincoln-Douglas": "",
    "Public Forum": "x",
    "Policy": ""
  },
  {
    "School": "Bloomington HS",
    "Coach": "Bloomington HS",
    "Email": "thorntonb@district87.org",
    "Phone": "+1 309-737-5174",
    "Congress": "x",
    "Lincoln-Douglas": "",
    "Public Forum": "",
    "Policy": ""
  },
  {
    "School": "Bolingbrook High School",
    "Coach": "Emmalee Buehler",
    "Email": "buehleres@vvsd.org",
    "Phone": "+1 330-988-3063",
    "Congress": "",
    "Lincoln-Douglas": "x",
    "Public Forum": "x",
    "Policy": ""
  },
  {
    "School": "British International School",
    "Coach": "Nicola Able",
    "Email": "nicola.able@bischicagosl.org",
    "Phone": "+1 312-866-4014",
    "Congress": "",
    "Lincoln-Douglas": "",
    "Public Forum": "x",
    "Policy": ""
  },
  {
    "School": "Buffalo Grove",
    "Coach": "Miguel Melgar",
    "Email": "melgardebate@gmail.com",
    "Phone": "+1 847-630-8429",
    "Congress": "",
    "Lincoln-Douglas": "x",
    "Public Forum": "x",
    "Policy": ""
  },
  {
    "School": "Carl Sandburg",
    "Coach": "Kris Kwak",
    "Email": "kkwak@d230.org",
    "Phone": "+1 708-205-0037",
    "Congress": "",
    "Lincoln-Douglas": "x",
    "Public Forum": "x",
    "Policy": ""
  },
  {
    "School": "Chesterton (Indiana)",
    "Coach": "Chris Lowery",
    "Email": "chslowery@gmail.com",
    "Phone": "+1 219-309-5316",
    "Congress": "x",
    "Lincoln-Douglas": "x",
    "Public Forum": "x",
    "Policy": "x"
  },
  {
    "School": "Chicago Catholic Forensic League",
    "Coach": "Mike Colletti",
    "Email": "mikecolletti529@gmail.com",
    "Phone": "+1 773-320-3390",
    "Congress": "x",
    "Lincoln-Douglas": "x",
    "Public Forum": "x",
    "Policy": "x"
  },
  {
    "School": "College Prep School of America",
    "Coach": "Nadia Joudeh",
    "Email": "nadia.joudeh@cpsaonline.org; asim.gaffar@cpsaonline.org",
    "Phone": "",
    "Congress": "",
    "Lincoln-Douglas": "x",
    "Public Forum": "x",
    "Policy": ""
  },
  {
    "School": "Conant",
    "Coach": "Gary Schumacher",
    "Email": "gschumacher@d211.org",
    "Phone": "",
    "Congress": "x",
    "Lincoln-Douglas": "",
    "Public Forum": "",
    "Policy": ""
  },
  {
    "School": "Conant",
    "Coach": "Elizabeth Dopke",
    "Email": "edopke@d211.org",
    "Phone": "",
    "Congress": "",
    "Lincoln-Douglas": "",
    "Public Forum": "x",
    "Policy": ""
  },
  {
    "School": "Dundee Crown",
    "Coach": "Shannon Petry",
    "Email": "shannon.petry@d300.org",
    "Phone": "+1 815-823-5090",
    "Congress": "x",
    "Lincoln-Douglas": "",
    "Public Forum": "",
    "Policy": ""
  },
  {
    "School": "Elk Grove",
    "Coach": "Matt Bohnenkamp",
    "Email": "Matthew.bohnenkamp@d214.org",
    "Phone": "+1 708-606-4399",
    "Congress": "x",
    "Lincoln-Douglas": "",
    "Public Forum": "",
    "Policy": ""
  },
  {
    "School": "Evanston Township",
    "Coach": "Clark Foster",
    "Email": "fosterc@eths202.org",
    "Phone": "+1 847-644-4673",
    "Congress": "x",
    "Lincoln-Douglas": "x",
    "Public Forum": "x",
    "Policy": "x"
  },
  {
    "School": "Fremd",
    "Coach": "Anna Ignatowicz",
    "Email": "aignatowicz@d211.org",
    "Phone": "+1 630-740-6292",
    "Congress": "",
    "Lincoln-Douglas": "x",
    "Public Forum": "x",
    "Policy": ""
  },
  {
    "School": "Fremd",
    "Coach": "Solinna Chong",
    "Email": "schong@d211.org",
    "Phone": "",
    "Congress": "x",
    "Lincoln-Douglas": "",
    "Public Forum": "",
    "Policy": ""
  },
  {
    "School": "Gibault",
    "Coach": "Don Murphy",
    "Email": "dmurphy@lemp-murphy.com",
    "Phone": "+1 618-444-0374",
    "Congress": "",
    "Lincoln-Douglas": "x",
    "Public Forum": "",
    "Policy": ""
  },
  {
    "School": "Glenbrook South",
    "Coach": "Alyssa Corrigan",
    "Email": "alucasbolin@glenbrook225.org",
    "Phone": "",
    "Congress": "",
    "Lincoln-Douglas": "",
    "Public Forum": "",
    "Policy": ""
  },
  {
    "School": "Granite City",
    "Coach": "Amy Pennell",
    "Email": "amy.pennell@gcsd9.net",
    "Phone": "+1 323-620-9482",
    "Congress": "x",
    "Lincoln-Douglas": "x",
    "Public Forum": "x",
    "Policy": ""
  },
  {
    "School": "Grant (Fox Lake)",
    "Coach": "Maxwell Boton",
    "Email": "mboton@grantbulldogs.org",
    "Phone": "",
    "Congress": "x",
    "Lincoln-Douglas": "",
    "Public Forum": "x",
    "Policy": ""
  },
  {
    "School": "Grayslake Central",
    "Coach": "Christopher D'Amico",
    "Email": "cdamico@d127.org",
    "Phone": "",
    "Congress": "x",
    "Lincoln-Douglas": "",
    "Public Forum": "",
    "Policy": ""
  },
  {
    "School": "Grayslake North",
    "Coach": "Dustin Zubert",
    "Email": "dzubert@d127.org",
    "Phone": "+1 847-710-0148",
    "Congress": "x",
    "Lincoln-Douglas": "",
    "Public Forum": "",
    "Policy": ""
  },
  {
    "School": "Hampshire",
    "Coach": "Lynda Bolding",
    "Email": "lynda.bolding@d300.org",
    "Phone": "+1 847-989-7033",
    "Congress": "x",
    "Lincoln-Douglas": "",
    "Public Forum": "",
    "Policy": ""
  },
  {
    "School": "Hersey",
    "Coach": "Jack Stanislaw",
    "Email": "Mcslaw1230@gmail.com",
    "Phone": "",
    "Congress": "x",
    "Lincoln-Douglas": "",
    "Public Forum": "",
    "Policy": ""
  },
  {
    "School": "Highland Park",
    "Coach": "Shawn Tanner",
    "Email": "stanner@dist113.org",
    "Phone": "+1 517-980-1470",
    "Congress": "x",
    "Lincoln-Douglas": "",
    "Public Forum": "x",
    "Policy": ""
  },
  {
    "School": "Hinsdale Central",
    "Coach": "",
    "Email": "",
    "Phone": "+1 630-209-4132",
    "Congress": "",
    "Lincoln-Douglas": "",
    "Public Forum": "x",
    "Policy": ""
  },
  {
    "School": "Holy Trinity",
    "Coach": "",
    "Email": "",
    "Phone": "+1 412-576-9666",
    "Congress": "",
    "Lincoln-Douglas": "x",
    "Public Forum": "",
    "Policy": ""
  },
  {
    "School": "Homewood Flossmoor",
    "Coach": "Katie Cole",
    "Email": "kcole@hf233.org",
    "Phone": "+1 708-217-9653",
    "Congress": "x",
    "Lincoln-Douglas": "x",
    "Public Forum": "x",
    "Policy": "x"
  },
  {
    "School": "IMSA",
    "Coach": "Leonard Lee",
    "Email": "leonardlee612@gmail.com",
    "Phone": "",
    "Congress": "x",
    "Lincoln-Douglas": "x",
    "Public Forum": "x",
    "Policy": ""
  },
  {
    "School": "Lake Forest High School",
    "Coach": "John Wanninger",
    "Email": "jwanninger@lfschools.net",
    "Phone": "+1 773-790-6871",
    "Congress": "x",
    "Lincoln-Douglas": "",
    "Public Forum": "",
    "Policy": ""
  },
  {
    "School": "Lake Zurich High School",
    "Coach": "Kim Philipp",
    "Email": "Kim.philipp@lz95.org",
    "Phone": "",
    "Congress": "",
    "Lincoln-Douglas": "x",
    "Public Forum": "x",
    "Policy": ""
  },
  {
    "School": "Lakes Community High School",
    "Coach": "Kris Scheidt",
    "Email": "",
    "Phone": "",
    "Congress": "",
    "Lincoln-Douglas": "x",
    "Public Forum": "x",
    "Policy": ""
  },
  {
    "School": "LaSalle-Peru",
    "Coach": "Mike Fisher*",
    "Email": "mfisher@lphs.net",
    "Phone": "+1 815-440-2755",
    "Congress": "x",
    "Lincoln-Douglas": "x",
    "Public Forum": "x",
    "Policy": ""
  },
  {
    "School": "Libertyville",
    "Coach": "Sarah Greenswag",
    "Email": "Sarah.Greenswag@d128.org",
    "Phone": "+1 847-702-0509",
    "Congress": "",
    "Lincoln-Douglas": "x",
    "Public Forum": "x",
    "Policy": ""
  },
  {
    "School": "Loyola Academy",
    "Coach": "Nicole Roman",
    "Email": "nroman@loy.org",
    "Phone": "+1 847-987-2101",
    "Congress": "",
    "Lincoln-Douglas": "x",
    "Public Forum": "x",
    "Policy": ""
  },
  {
    "School": "Lyons",
    "Coach": "Tom Swiontek",
    "Email": "tswiontek@lths.net",
    "Phone": "+1 630-479-0275",
    "Congress": "x",
    "Lincoln-Douglas": "x",
    "Public Forum": "",
    "Policy": ""
  },
  {
    "School": "Mascoutah High School",
    "Coach": "Jessica Ward",
    "Email": "wardjl@msd19.org",
    "Phone": "",
    "Congress": "",
    "Lincoln-Douglas": "",
    "Public Forum": "",
    "Policy": ""
  },
  {
    "School": "Moline",
    "Coach": "Colette Guerdet",
    "Email": "cguerdet@molineschools.org",
    "Phone": "",
    "Congress": "",
    "Lincoln-Douglas": "",
    "Public Forum": "",
    "Policy": ""
  },
  {
    "School": "Mundelein High School",
    "Coach": "Sydney Hamilton",
    "Email": "shamilton@d120.org",
    "Phone": "",
    "Congress": "",
    "Lincoln-Douglas": "x",
    "Public Forum": "x",
    "Policy": ""
  },
  {
    "School": "Naperville Central",
    "Coach": "Randy Smith",
    "Email": "rsmith@naperville203.org",
    "Phone": "+1 630-877-7178",
    "Congress": "x",
    "Lincoln-Douglas": "",
    "Public Forum": "",
    "Policy": ""
  },
  {
    "School": "New Trier",
    "Coach": "Aaron Vinson",
    "Email": "vinsona@newtrier.k12.il.us",
    "Phone": "+1 937-245-0110",
    "Congress": "x",
    "Lincoln-Douglas": "x",
    "Public Forum": "x",
    "Policy": "x"
  },
  {
    "School": "Newman Central Catholic HS",
    "Coach": "Ryan Sotelo",
    "Email": "rsotelo@newmancchs.org",
    "Phone": "",
    "Congress": "",
    "Lincoln-Douglas": "",
    "Public Forum": "",
    "Policy": ""
  },
  {
    "School": "Northridge Prep",
    "Coach": "",
    "Email": "",
    "Phone": "+1 312-342-3275",
    "Congress": "",
    "Lincoln-Douglas": "x",
    "Public Forum": "x",
    "Policy": ""
  },
  {
    "School": "Notre Dame College Prep",
    "Coach": "Robert Lashley ",
    "Email": "rlashley@nddons.org",
    "Phone": "+1 312-505-2616",
    "Congress": "x",
    "Lincoln-Douglas": "",
    "Public Forum": "",
    "Policy": ""
  },
  {
    "School": "Palatine",
    "Coach": "Samantha Dolen",
    "Email": "sdolen@d211.org",
    "Phone": "+1 224-595-2906",
    "Congress": "",
    "Lincoln-Douglas": "x",
    "Public Forum": "x",
    "Policy": ""
  },
  {
    "School": "Peoria Notre Dame High School",
    "Coach": "Leah Bousky",
    "Email": "l.daugherty@pndhs.org",
    "Phone": "+1 630-877-6302",
    "Congress": "",
    "Lincoln-Douglas": "",
    "Public Forum": "x",
    "Policy": ""
  },
  {
    "School": "Red Bud",
    "Coach": "Brian Magee",
    "Email": "bmagee@redbud132.org",
    "Phone": "+1 618-972-0993",
    "Congress": "",
    "Lincoln-Douglas": "",
    "Public Forum": "x",
    "Policy": ""
  },
  {
    "School": "Rich Township High School",
    "Coach": "Takema Taylor",
    "Email": "ttaylor1@rich227.org",
    "Phone": "+1 815-214-1722",
    "Congress": "",
    "Lincoln-Douglas": "x",
    "Public Forum": "x",
    "Policy": ""
  },
  {
    "School": "Richwoods High School",
    "Coach": "Alyssa  Emanuelson",
    "Email": "",
    "Phone": "+1 815-252-3471",
    "Congress": "x",
    "Lincoln-Douglas": "x",
    "Public Forum": "x",
    "Policy": ""
  },
  {
    "School": "Rock Island",
    "Coach": "Jeffry Duster",
    "Email": "jeffry.duster@rimsd41.org",
    "Phone": "+1 309-798-3276",
    "Congress": "",
    "Lincoln-Douglas": "",
    "Public Forum": "x",
    "Policy": ""
  },
  {
    "School": "Rockford East",
    "Coach": "Jacqueline Landreth",
    "Email": "jacqueline.landreth@rps205.com",
    "Phone": "\u202a7792200132\u202c",
    "Congress": "",
    "Lincoln-Douglas": "",
    "Public Forum": "x",
    "Policy": ""
  },
  {
    "School": "Rolling Meadows",
    "Coach": "Tim Waters",
    "Email": "Tim.waters@d214.org",
    "Phone": "+1 847-718-5945",
    "Congress": "x",
    "Lincoln-Douglas": "",
    "Public Forum": "",
    "Policy": ""
  },
  {
    "School": "Schaumburg",
    "Coach": "Carl Schwartz",
    "Email": "cschwartz@d211.org",
    "Phone": "+1 847-791-6844",
    "Congress": "x",
    "Lincoln-Douglas": "x",
    "Public Forum": "x",
    "Policy": ""
  },
  {
    "School": "St. Charles East",
    "Coach": "Kyle Libberton",
    "Email": "kyle.libberton@d303.org",
    "Phone": "",
    "Congress": "",
    "Lincoln-Douglas": "x",
    "Public Forum": "x",
    "Policy": ""
  },
  {
    "School": "St. Charles North",
    "Coach": "Gary Riley",
    "Email": "",
    "Phone": "",
    "Congress": "x",
    "Lincoln-Douglas": "",
    "Public Forum": "x",
    "Policy": ""
  },
  {
    "School": "St. Edward",
    "Coach": "Wendy Kelly",
    "Email": "",
    "Phone": "+1 815-382-7930",
    "Congress": "",
    "Lincoln-Douglas": "x",
    "Public Forum": "x",
    "Policy": ""
  },
  {
    "School": "St. Ignatius",
    "Coach": "Hallie Fahey",
    "Email": "hallie.fahey@ignatius.org",
    "Phone": "",
    "Congress": "",
    "Lincoln-Douglas": "",
    "Public Forum": "",
    "Policy": ""
  },
  {
    "School": "St. Patrick High School",
    "Coach": "Laura Brask",
    "Email": "",
    "Phone": "+1 847-946-7669",
    "Congress": "",
    "Lincoln-Douglas": "",
    "Public Forum": "x",
    "Policy": ""
  },
  {
    "School": "Staunton High School",
    "Coach": "",
    "Email": "mmccalla@stauntonschools.org",
    "Phone": "",
    "Congress": "",
    "Lincoln-Douglas": "",
    "Public Forum": "",
    "Policy": ""
  },
  {
    "School": "Triad High School",
    "Coach": "Kenneth Rodgers",
    "Email": "kenneth.rodgers@tcusd2.org",
    "Phone": "+1 618-910-7669",
    "Congress": "",
    "Lincoln-Douglas": "x",
    "Public Forum": "x",
    "Policy": ""
  },
  {
    "School": "Universal School",
    "Coach": "Lana Mahairi",
    "Email": "lmahairi@universalschool.org",
    "Phone": "",
    "Congress": "",
    "Lincoln-Douglas": "",
    "Public Forum": "",
    "Policy": ""
  },
  {
    "School": "University High School - Normal",
    "Coach": "Brian Rohman",
    "Email": "bmrohma@ilstu.edu",
    "Phone": "+1 309-264-1546",
    "Congress": "x",
    "Lincoln-Douglas": "x",
    "Public Forum": "x",
    "Policy": ""
  },
  {
    "School": "University of Chicago Laboratory Schools",
    "Coach": "Sonny Patel",
    "Email": "uclabdb8@gmail.com",
    "Phone": "+1 847-312-0543",
    "Congress": "",
    "Lincoln-Douglas": "",
    "Public Forum": "",
    "Policy": "x"
  },
  {
    "School": "West Leyden High School",
    "Coach": "Kim Berliner",
    "Email": "kberliner@leyden212.org",
    "Phone": "",
    "Congress": "",
    "Lincoln-Douglas": "",
    "Public Forum": "",
    "Policy": ""
  },
  {
    "School": "Wheeling",
    "Coach": "",
    "Email": "",
    "Phone": "",
    "Congress": "x",
    "Lincoln-Douglas": "",
    "Public Forum": "",
    "Policy": ""
  },
  {
    "School": "",
    "Coach": "Stephanie Liverant - assistant",
    "Email": "sliverant@d127.org",
    "Phone": "+1 847-530-2712",
    "Congress": "",
    "Lincoln-Douglas": "",
    "Public Forum": "",
    "Policy": ""
  },
  {
    "School": "",
    "Coach": "Adam Sherman-assistant",
    "Email": "asherman@rich227.org",
    "Phone": "+1 847-254-5671",
    "Congress": "",
    "Lincoln-Douglas": "x",
    "Public Forum": "x",
    "Policy": ""
  },
  {
    "School": "",
    "Coach": "Rebekah Hoffman",
    "Email": "rahoffm@ilstu.edu",
    "Phone": "+1 217-493-0859",
    "Congress": "",
    "Lincoln-Douglas": "",
    "Public Forum": "",
    "Policy": ""
  },
  {
    "School": "",
    "Coach": "Adeline Schultz",
    "Email": "ajschultz6@gmail.com",
    "Phone": "+1 309-531-2337",
    "Congress": "",
    "Lincoln-Douglas": "",
    "Public Forum": "",
    "Policy": ""
  },
  {
    "School": "",
    "Coach": "Alex Redell",
    "Email": "aeredel@ilstu.edu",
    "Phone": "+1 309-349-7540",
    "Congress": "",
    "Lincoln-Douglas": "",
    "Public Forum": "",
    "Policy": ""
  },
  {
    "School": "",
    "Coach": "Dave Weston",
    "Email": "westond@newtrier.k12.il.us",
    "Phone": "",
    "Congress": "",
    "Lincoln-Douglas": "",
    "Public Forum": "",
    "Policy": ""
  },
  {
    "School": "",
    "Coach": "Jacob Randulich",
    "Email": "jrandulich@d230.org",
    "Phone": "",
    "Congress": "",
    "Lincoln-Douglas": "",
    "Public Forum": "",
    "Policy": ""
  },
  {
    "School": "",
    "Coach": "Amal Abdellatif",
    "Email": "aabdellatif@d230.org",
    "Phone": "",
    "Congress": "",
    "Lincoln-Douglas": "x",
    "Public Forum": "",
    "Policy": ""
  },
  {
    "School": "",
    "Coach": "Romana Kovacevic",
    "Email": "rkovacevic@d230.org",
    "Phone": "+1 708-289-1777",
    "Congress": "",
    "Lincoln-Douglas": "",
    "Public Forum": "x",
    "Policy": ""
  },
  {
    "School": "",
    "Coach": "Brian Jerger",
    "Email": "bjerger@fenwickfriars.com",
    "Phone": "+1 708-704-7726",
    "Congress": "x",
    "Lincoln-Douglas": "x",
    "Public Forum": "x",
    "Policy": ""
  },
  {
    "School": "",
    "Coach": "Dorothy Robak",
    "Email": "drobak@d211.org",
    "Phone": "",
    "Congress": "",
    "Lincoln-Douglas": "x",
    "Public Forum": "x",
    "Policy": ""
  },
  {
    "School": "",
    "Coach": "Caitlin Clark-Johnson",
    "Email": "cmjohnson@d211.org",
    "Phone": "",
    "Congress": "x",
    "Lincoln-Douglas": "x",
    "Public Forum": "x",
    "Policy": ""
  },
  {
    "School": "",
    "Coach": "Cliff Paul",
    "Email": "",
    "Phone": "",
    "Congress": "",
    "Lincoln-Douglas": "x",
    "Public Forum": "x",
    "Policy": ""
  },
  {
    "School": "",
    "Coach": "Elizabeth Dopke",
    "Email": "edopke@d211.org",
    "Phone": "",
    "Congress": "x",
    "Lincoln-Douglas": "",
    "Public Forum": "x",
    "Policy": ""
  },
  {
    "School": "",
    "Coach": "Tara Tate",
    "Email": "ttate@glenbrook225.org",
    "Phone": "",
    "Congress": "x",
    "Lincoln-Douglas": "x",
    "Public Forum": "",
    "Policy": "x"
  },
  {
    "School": "",
    "Coach": "Amy Lovi",
    "Email": "alovi@barrington220.org",
    "Phone": "",
    "Congress": "x",
    "Lincoln-Douglas": "",
    "Public Forum": "",
    "Policy": ""
  },
  {
    "School": "",
    "Coach": "Steve Heller",
    "Email": "sheller@d125.org",
    "Phone": "",
    "Congress": "x",
    "Lincoln-Douglas": "",
    "Public Forum": "",
    "Policy": ""
  },
  {
    "School": "",
    "Coach": "Saarah Mohammed",
    "Email": "Saarah.Mohammed@d214.org",
    "Phone": "",
    "Congress": "x",
    "Lincoln-Douglas": "",
    "Public Forum": "",
    "Policy": ""
  },
  {
    "School": "",
    "Coach": "Tom Smith",
    "Email": "Tom.Smith@d214.org",
    "Phone": "+1 847-226-0259",
    "Congress": "",
    "Lincoln-Douglas": "",
    "Public Forum": "",
    "Policy": ""
  },
  {
    "School": "",
    "Coach": "Mari Brown",
    "Email": "mbrown@dist113.org",
    "Phone": "",
    "Congress": "x",
    "Lincoln-Douglas": "",
    "Public Forum": "x",
    "Policy": ""
  },
  {
    "School": "",
    "Coach": "Jennifer Barton",
    "Email": "jbarton@nddons.org",
    "Phone": "",
    "Congress": "",
    "Lincoln-Douglas": "",
    "Public Forum": "",
    "Policy": ""
  },
  {
    "School": "",
    "Coach": "Alexandra LeFlore",
    "Email": "aleflore@d125.org",
    "Phone": "",
    "Congress": "",
    "Lincoln-Douglas": "",
    "Public Forum": "x",
    "Policy": ""
  },
  {
    "School": "",
    "Coach": "Sonny Patel",
    "Email": "sonnygpatel@gmail.com",
    "Phone": "+1 847-312-0543",
    "Congress": "",
    "Lincoln-Douglas": "",
    "Public Forum": "",
    "Policy": ""
  },
  {
    "School": "",
    "Coach": "Jaylene Murphy",
    "Email": "jaylene.murphy@sbcglobal.net",
    "Phone": "+1 618-444-0462",
    "Congress": "",
    "Lincoln-Douglas": "X",
    "Public Forum": "",
    "Policy": ""
  },
  {
    "School": "",
    "Coach": "Jamie Reuben",
    "Email": "jamie.reuben@d128.org",
    "Phone": "",
    "Congress": "",
    "Lincoln-Douglas": "",
    "Public Forum": "",
    "Policy": ""
  },
  {
    "School": "",
    "Coach": "Bill Brandstrader",
    "Email": "wrb@loy.org",
    "Phone": "",
    "Congress": "",
    "Lincoln-Douglas": "",
    "Public Forum": "",
    "Policy": ""
  },
  {
    "School": "",
    "Coach": "Leslie Schock",
    "Email": "lschock@d211.org",
    "Phone": "+1 773-895-6775",
    "Congress": "",
    "Lincoln-Douglas": "",
    "Public Forum": "",
    "Policy": ""
  },
  {
    "School": "",
    "Coach": "Rebekah Hoffman",
    "Email": "rahoffm@ilstu.edu",
    "Phone": "+1 217-493-0859",
    "Congress": "X",
    "Lincoln-Douglas": "X",
    "Public Forum": "X",
    "Policy": ""
  },
  {
    "School": "",
    "Coach": "Meghan Gleason",
    "Email": "mgleason@leyden212.org",
    "Phone": "",
    "Congress": "",
    "Lincoln-Douglas": "",
    "Public Forum": "",
    "Policy": ""
  }
]